namekox_etcd/__init__.py
namekox_etcd/constants.py
namekox_etcd/exceptions.py
namekox_etcd/cli/__init__.py
namekox_etcd/cli/subctx/__init__.py
namekox_etcd/cli/subctx/etcd3.py
namekox_etcd/core/__init__.py
namekox_etcd/core/allotter.py
namekox_etcd/core/client.py
namekox_etcd/core/proxy.py
namekox_etcd/core/dependencies/__init__.py
namekox_etcd/core/dependencies/etcd3.py
namekox_etcd-0.0.5.dist-info/LICENSE
namekox_etcd-0.0.5.dist-info/METADATA
namekox_etcd-0.0.5.dist-info/WHEEL
namekox_etcd-0.0.5.dist-info/top_level.txt
namekox_etcd-0.0.5.dist-info/zip-safe
namekox_etcd-0.0.5.dist-info/RECORD
